{
  "sections": {
    "flickity-slider": {
      "type": "flickity-header-carousel",
      "settings": {
        "collection": "home-page-slider"
      }
    },
    "single_collection": {
      "type": "section-single-collection",
      "settings": {
        "title": "Check this collection",
        "collection": "bathroom-deals",
        "show_cart_button": false,
        "layout": "pipe_corner",
        "color": "blue",
        "card_color": "gray"
      }
    },
    "call-to-action": {
      "type": "call-to-action",
      "settings": {
        "cta_title": "Read more about",
        "product": "leakmate-emergency-leak-stop-tool",
        "image_position": "left",
        "cta_button_text": "Read More..."
      }
    },
    "collection-slider": {
      "type": "collection-slider",
      "settings": {
        "title": "This month sales",
        "style": "blue",
        "collection": "bathroom-deals"
      }
    },
    "single-product-with-extras": {
      "type": "section-single-product",
      "settings": {
        "title": "Check this product",
        "product": "cashel-traditional-free-standing-bath-white-1720-x-776-mm",
        "layout": "pipe_bottom"
      }
    },
    "featured-collection-v2": {
      "type": "smallmans-featured-collection-v2",
      "settings": {
        "collection": "bathroom-deals"
      }
    },
    "call-to-action-v2": {
      "type": "smallmans-calltoaction-v2",
      "settings": {
        "title":"Check this collection",
        "description":"Halvah croissant candy canes bonbon candy. Apple pie jelly beans topping carrot cake danish tart cake cheesecake.",
        "buttontext":"Read more"
      }
    }
  },
  "order": [
    "flickity-slider",
    "single_collection",
    "call-to-action",
    "collection-slider",
    "single-product-with-extras",
    "featured-collection-v2",
    "call-to-action-v2"
  ]
}
